{
  "Violin": {
    "JrNn2Ns7k-g": [[0, 10332]]
  },
  "Viola": {
    "-fTiMdxqL1o": [[94, 5171]],
    "4KujFOTKzN0": [[0, 8705]],
    "80pVi2NQ66c": [[402, 1101], [1302, 2596], [2697, 3679], [3781, 6150]],
    "IGCx-Bdi-50": [[0, 11293]],
    "SOU5JJ_sPh4": [[0, 5103]],
    "SsbB7f_Z-io": [[0, 5193]],
    "W-ghmZkTtFE": [[0, 13076]],
    "WZgPcjChMsY": [[0, 8382]],
    "_fp_jfzBgts": [[101, 10887]],
    "hjvtVopqflI": [[0, 8562]],
    "jvZgxmVGR4A": [[0, 7470]],
    "lLml8_BjQO8": [[81, 2051], [2075, 3398]],
    "p0CzWz7DzVo": [[0, 3733]]
  }
}
